weeve_modules/__init__.py
weeve_modules/add_graceful_termination.py
weeve_modules/listener.py
weeve_modules/listener_callback_function.py
weeve_modules/logger.py
weeve_modules/processing_thread.py
weeve_modules/request_handler.py
weeve_modules/send.py
weeve_modules/version.py
weeve_modules-1.0.0.dist-info/METADATA
weeve_modules-1.0.0.dist-info/WHEEL
weeve_modules-1.0.0.dist-info/licenses/LICENSE
weeve_modules-1.0.0.dist-info/RECORD
