Metadata-Version: 2.1
Name: weeve_modules
Version: 1.0.0
Summary: Python package supporting weeve modules infrastructure.
Project-URL: weeve, https://www.weeve.network
Project-URL: How to create a weeve module, https://docs.weeve.engineering/guides/how-to-create-a-weeve-module
Project-URL: GitHub, https://github.com/weeve-modules/weeve-modules-python-package
Project-URL: Bug Tracker, https://github.com/weeve-modules/weeve-modules-python-package/issues
Author-email: Jakub Grzelak <jakub.grzelak@weeve.network>
Maintainer-email: Jakub Grzelak <jakub.grzelak@weeve.network>, Sanyam Arya <sanyam.arya@weeve.network>, Paul Gaiduk <paul.gaiduk@weeve.network>
License-File: LICENSE
Keywords: Internet of Things,IoT,Machine Economy,modules,weeve
Classifier: License :: OSI Approved :: GNU General Public License v3 (GPLv3)
Classifier: Operating System :: OS Independent
Classifier: Programming Language :: Python :: 3
Requires-Python: >=3.7
Requires-Dist: bottle>=0.12.25
Requires-Dist: requests>=2.28.2
